Metadata-Version: 2.1
Name: Mensajes-tinyjav0713
Version: 6.0
Summary: Paquete que permite saludar y despedir
Author: Javier Rivera Romero
Author-email: tinyjav@hotmail.com
Classifier: Environment :: Console
Classifier: Intended Audience :: Developers
Classifier: License :: OSI Approved :: MIT License
Classifier: Operating System :: OS Independent
Classifier: Programming Language :: Python
Classifier: Programming Language :: Python :: 3.10
Classifier: Topic :: Utilities
License-File: LICENSE
Requires-Dist: numpy (>=1.24.3)
